Workbook

Sheet Inventory
A1: SKU | B1: Product | C1: Qty | D1: Unit Price | E1: Subtotal | F1: Tax (10%) | G1: Total
A2: SKU-001 | B2: Wireless Mouse | C2: 25 | D2: 19.99 | E2: =C2*D2 | F2: =E2*0.1 | G2: =E2+F2
A3: SKU-002 | B3: Mechanical Keyboard | C3: 12 | D3: 89.5 | E3: =C3*D3 | F3: =E3*0.1 | G3: =E3+F3
A4: SKU-003 | B4: USB-C Hub | C4: 40 | D4: 34 | E4: =C4*D4 | F4: =E4*0.1 | G4: =E4+F4
A5: SKU-004 | B5: 27" Monitor | C5: 8 | D5: 299.99 | E5: =C5*D5 | F5: =E5*0.1 | G5: =E5+F5
A6: SKU-005 | B6: Webcam HD | C6: 15 | D6: 59.95 | E6: =C6*D6 | F6: =E6*0.1 | G6: =E6+F6
A7: SKU-006 | B7: Desk Lamp | C7: 30 | D7: 24.5 | E7: =C7*D7 | F7: =E7*0.1 | G7: =E7+F7
A8: SKU-007 | B8: Office Chair | C8: 5 | D8: 219 | E8: =C8*D8 | F8: =E8*0.1 | G8: =E8+F8
A9: SKU-008 | B9: Standing Desk | C9: 3 | D9: 449 | E9: =C9*D9 | F9: =E9*0.1 | G9: =E9+F9
B10: TOTAL | C10: =SUM(C2:C9) | E10: =SUM(E2:E9) | F10: =SUM(F2:F9) | G10: =SUM(G2:G9)

Sheet Sales 2026
A1: Date | B1: Region | C1: Rep | D1: Units | E1: Revenue | F1: Commission (8%) | G1: Status
A2: 2026-01-05 | B2: North | C2: Alice | D2: 120 | E2: 4800 | F2: =E2*0.08 | G2: =IF(E2>=6000,"Bonus","Standard")
A3: 2026-01-18 | B3: South | C3: Bob | D3: 85 | E3: 3200 | F3: =E3*0.08 | G3: =IF(E3>=6000,"Bonus","Standard")
A4: 2026-02-02 | B4: East | C4: Carlos | D4: 210 | E4: 9450 | F4: =E4*0.08 | G4: =IF(E4>=6000,"Bonus","Standard")
A5: 2026-02-22 | B5: West | C5: Diana | D5: 60 | E5: 2400 | F5: =E5*0.08 | G5: =IF(E5>=6000,"Bonus","Standard")
A6: 2026-03-10 | B6: North | C6: Alice | D6: 175 | E6: 7000 | F6: =E6*0.08 | G6: =IF(E6>=6000,"Bonus","Standard")
A7: 2026-03-28 | B7: South | C7: Bob | D7: 130 | E7: 5200 | F7: =E7*0.08 | G7: =IF(E7>=6000,"Bonus","Standard")
A8: 2026-04-12 | B8: East | C8: Carlos | D8: 240 | E8: 10800 | F8: =E8*0.08 | G8: =IF(E8>=6000,"Bonus","Standard")
A9: 2026-04-30 | B9: West | C9: Diana | D9: 95 | E9: 3800 | F9: =E9*0.08 | G9: =IF(E9>=6000,"Bonus","Standard")
A10: 2026-05-15 | B10: North | C10: Alice | D10: 160 | E10: 6400 | F10: =E10*0.08 | G10: =IF(E10>=6000,"Bonus","Standard")
A11: 2026-06-01 | B11: South | C11: Bob | D11: 145 | E11: 5800 | F11: =E11*0.08 | G11: =IF(E11>=6000,"Bonus","Standard")
C12: TOTAL | D12: =SUM(D2:D11) | E12: =SUM(E2:E11) | F12: =SUM(F2:F11)
C13: AVG | D13: =AVERAGE(D2:D11) | E13: =AVERAGE(E2:E11) | F13: =AVERAGE(F2:F11)
C14: MAX | D14: =MAX(D2:D11) | E14: =MAX(E2:E11) | F14: =MAX(F2:F11)

Sheet Employees
A1: ID | B1: Name | C1: Department | D1: Hire Date | E1: Salary | F1: Annual Bonus | G1: Years
A2: 1001 | B2: Anna Lee | C2: Engineering | D2: 2019-03-15 | E2: 95000 | F2: =E2*0.05 | G2: =DATEDIF(DATEVALUE(D2),DATEVALUE("2026-06-16"),"Y")
A3: 1002 | B3: Brian Cho | C3: Sales | D3: 2021-07-01 | E3: 72000 | F3: =E3*0.05 | G3: =DATEDIF(DATEVALUE(D3),DATEVALUE("2026-06-16"),"Y")
A4: 1003 | B4: Chen Wei | C4: Engineering | D4: 2018-11-20 | E4: 102000 | F4: =E4*0.05 | G4: =DATEDIF(DATEVALUE(D4),DATEVALUE("2026-06-16"),"Y")
A5: 1004 | B5: Dmitri Volkov | C5: Marketing | D5: 2022-02-10 | E5: 68000 | F5: =E5*0.05 | G5: =DATEDIF(DATEVALUE(D5),DATEVALUE("2026-06-16"),"Y")
A6: 1005 | B6: Elena Ruiz | C6: HR | D6: 2020-09-05 | E6: 75000 | F6: =E6*0.05 | G6: =DATEDIF(DATEVALUE(D6),DATEVALUE("2026-06-16"),"Y")
A7: 1006 | B7: Farah Khan | C7: Engineering | D7: 2023-01-12 | E7: 88000 | F7: =E7*0.05 | G7: =DATEDIF(DATEVALUE(D7),DATEVALUE("2026-06-16"),"Y")
A8: 1007 | B8: Greg Holm | C8: Finance | D8: 2017-05-22 | E8: 110000 | F8: =E8*0.05 | G8: =DATEDIF(DATEVALUE(D8),DATEVALUE("2026-06-16"),"Y")
C9: COUNT | D9: =COUNTA(B2:B8) | E9: =SUM(E2:E8) | F9: =SUM(F2:F8)

Sheet Budget
A1: Category | B1: Planned | C1: Actual | D1: Variance | E1: % Used | F1: Flag
A2: Salaries | B2: 450000 | C2: 462000 | D2: =C2-B2 | E2: =C2/B2 | F2: =IF(D2>0,"OVER","OK")
A3: Marketing | B3: 80000 | C3: 74500 | D3: =C3-B3 | E3: =C3/B3 | F3: =IF(D3>0,"OVER","OK")
A4: R&D | B4: 220000 | C4: 235000 | D4: =C4-B4 | E4: =C4/B4 | F4: =IF(D4>0,"OVER","OK")
A5: Office | B5: 35000 | C5: 28900 | D5: =C5-B5 | E5: =C5/B5 | F5: =IF(D5>0,"OVER","OK")
A6: Travel | B6: 45000 | C6: 51200 | D6: =C6-B6 | E6: =C6/B6 | F6: =IF(D6>0,"OVER","OK")
A7: Software | B7: 60000 | C7: 58700 | D7: =C7-B7 | E7: =C7/B7 | F7: =IF(D7>0,"OVER","OK")
A8: Misc | B8: 15000 | C8: 12300 | D8: =C8-B8 | E8: =C8/B8 | F8: =IF(D8>0,"OVER","OK")
A9: TOTAL | B9: =SUM(B2:B8) | C9: =SUM(C2:C8) | D9: =SUM(D2:D8) | E9: =C9/B9

Sheet Summary
A1: Metric | B1: Value
A2: Total Inventory Items | B2: =Inventory!C10
A3: Total Inventory Value | B3: =Inventory!G10
A4: Total 2026 Revenue | B4: =SUM('Sales 2026'!E2:E11)
A5: Avg Sale Revenue | B5: =AVERAGE('Sales 2026'!E2:E11)
A6: Headcount | B6: =COUNTA(Employees!B2:B8)
A7: Payroll | B7: =SUM(Employees!E2:E8)
A8: Budget Variance | B8: =SUM(Budget!D2:D8)
